fntypes/__init__.py
fntypes/co.py
fntypes/error.py
fntypes/option.py
fntypes/py.typed
fntypes/result/__init__.py
fntypes/result/log_factory.py
fntypes/result/result.py
fntypes/tools/__init__.py
fntypes/tools/runtime_generic.py
fntypes/tools/unwrapping.py
fntypes/variative.py
fntypes-0.1.4.post3.dist-info/METADATA
fntypes-0.1.4.post3.dist-info/WHEEL
fntypes-0.1.4.post3.dist-info/RECORD
