Metadata-Version: 2.1
Name: fntypes
Version: 0.1.4.post3
Summary: 
Author: timoniq
Requires-Python: >=3.11,<4.0
Classifier: Programming Language :: Python :: 3
Classifier: Programming Language :: Python :: 3.11
